majormode/__init__.py
majormode/mercurius/__init__.py
majormode/mercurius/service/__init__.py
majormode/mercurius/service/place/__init__.py
majormode/mercurius/service/place/place_service.py
mercurius_restful_api_server_library-1.2.22.dist-info/METADATA
mercurius_restful_api_server_library-1.2.22.dist-info/WHEEL
mercurius_restful_api_server_library-1.2.22.dist-info/top_level.txt
mercurius_restful_api_server_library-1.2.22.dist-info/RECORD
