Metadata-Version: 2.1
Name: mercurius-restful-api-server-library
Version: 1.2.22
Summary: Mercurius RESTful API Server Python Library
Home-page: UNKNOWN
Author: Daniel CAUNE
Author-email: daniel.caune@gmail.com
License: MIT
Platform: any
Classifier: Development Status :: 5 - Production/Stable
Classifier: License :: OSI Approved :: MIT License
Classifier: Operating System :: OS Independent
Classifier: Programming Language :: Python
Classifier: Topic :: Software Development :: Libraries :: Python Modules
Requires-Python: >=3
Requires-Dist: pylibmc
Requires-Dist: perseus-restful-api-framework
Requires-Dist: pipfile
Requires-Dist: setuptools
Requires-Dist: wheel
Requires-Dist: mercurius-core-library
